pybedrock.libs/libstdc++-fd9f4683.so.6.0.28
pybedrock.libs/libgcc_s-4e37474d.so.1
pybedrock/__init__.py
pybedrock/main.py
pybedrock/cmodules/lib/libleveldbhandler.so
pybedrock-0.0.7.dist-info/LICENSE
pybedrock-0.0.7.dist-info/WHEEL
pybedrock-0.0.7.dist-info/top_level.txt
pybedrock-0.0.7.dist-info/RECORD
pybedrock-0.0.7.dist-info/METADATA
