Metadata-Version: 2.1
Name: pybedrock
Version: 0.0.7
Summary: A Python package to read/write Minecraft Bedrock leveldb data
Home-page: https://github.com/obscraft23/pybedrock
Author: obscraft23
Author-email: obscraft23@gmail.com
License: MIT
Keywords: Minecraft Bedrock leveldb
Classifier: License :: OSI Approved :: MIT License
Classifier: Programming Language :: Python :: 3.6
Classifier: Programming Language :: Python :: 3.7
Classifier: Programming Language :: Python :: 3.8
Classifier: Programming Language :: Python :: 3.9
Classifier: Programming Language :: Python :: 3.10
Classifier: Programming Language :: Python :: 3.11
Classifier: Programming Language :: C++
License-File: LICENSE
Requires-Dist: numpy
